{
    "kind": "youtube#videoListResponse",
    "etag": "Ae9y7uQ4B4-7Fg0zz02PCuuHmVg",
    "items": [
        {
            "kind": "youtube#video",
            "etag": "ES_SMfPdcyGpwAaz0GxTgsuSn8U",
            "id": "pzAMnYkK2gY",
            "snippet": {
                "publishedAt": "2025-10-24T11:50:50Z",
                "channelId": "UCGUvUVuthSVOk0Kq34krOGA",
                "title": "𝐓𝐡𝐨𝐮𝐠𝐡 𝐭𝐡𝐞 𝐅𝐢𝐫𝐞 -ไฟในใจ [𝐑𝐞𝐦𝐚𝐬𝐭𝐞𝐫 𝐯𝐞𝐫𝐬𝐢𝐨𝐧] #𝐨𝐟𝐟𝐢𝐜𝐢𝐚𝐥𝐦𝐮𝐬𝐢𝐜𝐯𝐢𝐝𝐞𝐨 #𝐜𝐢𝐧𝐞𝐦𝐚𝐭𝐢𝐜𝐫𝐨𝐜𝐤",
                "description": "🔥ไฟในใจ [𝘛𝘩𝘰𝘶𝘨𝘩 𝘵𝘩𝘦 𝘍𝘪𝘳𝘦] แม้เจ็บปวดหัวใจ ก็รักเพียงเธอ #𝘮𝘶𝘴𝘪𝘤 #𝘛𝘩𝘰𝘶𝘨𝘩𝘵𝘩𝘦𝘧𝘪𝘳𝘦 #𝘤𝘪𝘯𝘦𝘮𝘢𝘵𝘪𝘤𝘳𝘰𝘤𝘬 \nเพลงนี้ถูกเขียนเนื้อขึ้นและทำดนตรี ด้วยอุปกรณ์เพียงชิ้นเดียว คือ โทรศัพท์ 𝘙𝘦𝘥𝘮𝘪 ปี𝟤𝟢𝟣𝟫 #𝘳𝘦𝘥𝘮𝘪𝘯𝘰𝘵𝘦𝟪𝘱𝘳𝘰   𝘓𝘺𝘳𝘪𝘤𝘴/𝘔𝘦𝘭𝘰𝘥𝘺: 𝘉𝘔𝘈.\n𝘝𝘰𝘤𝘢𝘭𝘴: 𝘉𝘔𝘈.\n𝘚𝘰𝘶𝘯𝘥 𝘮𝘪𝘹𝘦𝘳: 𝘉𝘶𝘳𝘢𝘱𝘩𝘢 𝘔𝘶𝘴𝘪𝘤 𝘈𝘳𝘦𝘯𝘢© \n\n© 𝟤𝟢𝟤𝟧 𝘉𝘔𝘈𝘢𝘳𝘦𝘯𝘢. 𝘈𝘭𝘭 𝘳𝘪𝘨𝘩𝘵𝘴 𝘳𝘦𝘴𝘦𝘳𝘷𝘦𝘥. เพลง: 𝘛𝘩𝘰𝘶𝘨𝘩 𝘵𝘩𝘦 𝘍𝘪𝘳𝘦 (𝑅𝑒𝑚𝑎𝑠𝑡𝑒𝑟𝑒𝑑)\n สร้างสรรค์และจัดจำหน่ายโดย 𝘉𝘔𝘈𝘢𝘳𝘦𝘯𝘢©",
                "thumbnails": {
                    "default": {
                        "url": "https://i.ytimg.com/vi/pzAMnYkK2gY/default.jpg",
                        "width": 120,
                        "height": 90
                    },
                    "medium": {
                        "url": "https://i.ytimg.com/vi/pzAMnYkK2gY/mqdefault.jpg",
                        "width": 320,
                        "height": 180
                    },
                    "high": {
                        "url": "https://i.ytimg.com/vi/pzAMnYkK2gY/hqdefault.jpg",
                        "width": 480,
                        "height": 360
                    },
                    "standard": {
                        "url": "https://i.ytimg.com/vi/pzAMnYkK2gY/sddefault.jpg",
                        "width": 640,
                        "height": 480
                    }
                },
                "channelTitle": "𝐁𝐮𝐫𝐚𝐩𝐡𝐚 𝐦𝐮𝐬𝐢𝐜 𝐚𝐫𝐞𝐧𝐚",
                "tags": [
                    "@BMAarena",
                    "เพลงร็อค",
                    "though the Fire",
                    "mv official",
                    "ไฟในใจ",
                    "เพลงรัก"
                ],
                "categoryId": "10",
                "liveBroadcastContent": "none",
                "defaultLanguage": "th",
                "localized": {
                    "title": "𝐓𝐡𝐨𝐮𝐠𝐡 𝐭𝐡𝐞 𝐅𝐢𝐫𝐞 -ไฟในใจ [𝐑𝐞𝐦𝐚𝐬𝐭𝐞𝐫 𝐯𝐞𝐫𝐬𝐢𝐨𝐧] #𝐨𝐟𝐟𝐢𝐜𝐢𝐚𝐥𝐦𝐮𝐬𝐢𝐜𝐯𝐢𝐝𝐞𝐨 #𝐜𝐢𝐧𝐞𝐦𝐚𝐭𝐢𝐜𝐫𝐨𝐜𝐤",
                    "description": "🔥ไฟในใจ [𝘛𝘩𝘰𝘶𝘨𝘩 𝘵𝘩𝘦 𝘍𝘪𝘳𝘦] แม้เจ็บปวดหัวใจ ก็รักเพียงเธอ #𝘮𝘶𝘴𝘪𝘤 #𝘛𝘩𝘰𝘶𝘨𝘩𝘵𝘩𝘦𝘧𝘪𝘳𝘦 #𝘤𝘪𝘯𝘦𝘮𝘢𝘵𝘪𝘤𝘳𝘰𝘤𝘬 \nเพลงนี้ถูกเขียนเนื้อขึ้นและทำดนตรี ด้วยอุปกรณ์เพียงชิ้นเดียว คือ โทรศัพท์ 𝘙𝘦𝘥𝘮𝘪 ปี𝟤𝟢𝟣𝟫 #𝘳𝘦𝘥𝘮𝘪𝘯𝘰𝘵𝘦𝟪𝘱𝘳𝘰   𝘓𝘺𝘳𝘪𝘤𝘴/𝘔𝘦𝘭𝘰𝘥𝘺: 𝘉𝘔𝘈.\n𝘝𝘰𝘤𝘢𝘭𝘴: 𝘉𝘔𝘈.\n𝘚𝘰𝘶𝘯𝘥 𝘮𝘪𝘹𝘦𝘳: 𝘉𝘶𝘳𝘢𝘱𝘩𝘢 𝘔𝘶𝘴𝘪𝘤 𝘈𝘳𝘦𝘯𝘢© \n\n© 𝟤𝟢𝟤𝟧 𝘉𝘔𝘈𝘢𝘳𝘦𝘯𝘢. 𝘈𝘭𝘭 𝘳𝘪𝘨𝘩𝘵𝘴 𝘳𝘦𝘴𝘦𝘳𝘷𝘦𝘥. เพลง: 𝘛𝘩𝘰𝘶𝘨𝘩 𝘵𝘩𝘦 𝘍𝘪𝘳𝘦 (𝑅𝑒𝑚𝑎𝑠𝑡𝑒𝑟𝑒𝑑)\n สร้างสรรค์และจัดจำหน่ายโดย 𝘉𝘔𝘈𝘢𝘳𝘦𝘯𝘢©"
                },
                "defaultAudioLanguage": "en"
            },
            "contentDetails": {
                "duration": "PT3M45S",
                "dimension": "2d",
                "definition": "hd",
                "caption": "false",
                "licensedContent": false,
                "contentRating": {},
                "projection": "rectangular"
            },
            "statistics": {
                "viewCount": "13725",
                "likeCount": "36",
                "favoriteCount": "0",
                "commentCount": "1"
            }
        }
    ],
    "pageInfo": {
        "totalResults": 1,
        "resultsPerPage": 1
    }
}