[
    {
        "kind": "youtube#commentThread",
        "etag": "KpJGdynrnDi7VyZadNuz7LxE1O0",
        "id": "UgzjjCg0DpwKspN4AsN4AaABAg",
        "snippet": {
            "channelId": "UCuF5t0ziFf7QfoR9_xlti1w",
            "videoId": "EpyaquDcw1s",
            "topLevelComment": {
                "kind": "youtube#comment",
                "etag": "U3IIMXEaU3NDB7pTBYAAOHyj9wI",
                "id": "UgzjjCg0DpwKspN4AsN4AaABAg",
                "snippet": {
                    "channelId": "UCuF5t0ziFf7QfoR9_xlti1w",
                    "videoId": "EpyaquDcw1s",
                    "textDisplay": "沢山の人に聴いてほしい！イチオシ曲☔️✨雨模様🙌✨",
                    "textOriginal": "沢山の人に聴いてほしい！イチオシ曲☔️✨雨模様🙌✨",
                    "authorDisplayName": "@muttumtum",
                    "authorProfileImageUrl": "https://yt3.ggpht.com/FExG_cIQt-l-HmWCcms4ncCPRE9-PBKX54_HZyn0jnL3U7dwHfnl_fcg3r_L2Z2zeSBmw_KLKw=s48-c-k-c0x00ffffff-no-rj",
                    "authorChannelUrl": "http://www.youtube.com/@muttumtum",
                    "authorChannelId": {
                        "value": "UCvKaAH71iyytnLl4IrF3BCg"
                    },
                    "canRate": true,
                    "viewerRating": "none",
                    "likeCount": 0,
                    "publishedAt": "2025-11-20T13:16:34Z",
                    "updatedAt": "2025-11-20T13:16:34Z"
                }
            },
            "canReply": true,
            "totalReplyCount": 0,
            "isPublic": true
        }
    },
    {
        "kind": "youtube#commentThread",
        "etag": "uE_aUMmyrbuCzO8JZTsmTuwgXqU",
        "id": "UgwUGsS3-pETDVzNBU14AaABAg",
        "snippet": {
            "channelId": "UCuF5t0ziFf7QfoR9_xlti1w",
            "videoId": "EpyaquDcw1s",
            "topLevelComment": {
                "kind": "youtube#comment",
                "etag": "Sm84Up-Y1tI2K-EWrBtSnKBSObs",
                "id": "UgwUGsS3-pETDVzNBU14AaABAg",
                "snippet": {
                    "channelId": "UCuF5t0ziFf7QfoR9_xlti1w",
                    "videoId": "EpyaquDcw1s",
                    "textDisplay": "素敵な動画と音楽🎵楽しかった☺️",
                    "textOriginal": "素敵な動画と音楽🎵楽しかった☺️",
                    "authorDisplayName": "@hanakano-ex2ie",
                    "authorProfileImageUrl": "https://yt3.ggpht.com/Hd1YK_0aZ2E9vsNZWuwfHJamjpvGCUJhvMlRDFqjOJWsd3M7-p7xspWlKJMTd_OlwHT38txT=s48-c-k-c0x00ffffff-no-rj",
                    "authorChannelUrl": "http://www.youtube.com/@hanakano-ex2ie",
                    "authorChannelId": {
                        "value": "UCeY1fL3G5N4MBFQIpnpr1BA"
                    },
                    "canRate": true,
                    "viewerRating": "none",
                    "likeCount": 0,
                    "publishedAt": "2025-11-20T13:16:17Z",
                    "updatedAt": "2025-11-20T13:16:17Z"
                }
            },
            "canReply": true,
            "totalReplyCount": 0,
            "isPublic": true
        }
    },
    {
        "kind": "youtube#commentThread",
        "etag": "GOAOTpR027drYdNNKxGla6Tj9cg",
        "id": "UgyTDcojDeOvis4AM0B4AaABAg",
        "snippet": {
            "channelId": "UCuF5t0ziFf7QfoR9_xlti1w",
            "videoId": "EpyaquDcw1s",
            "topLevelComment": {
                "kind": "youtube#comment",
                "etag": "OIeGjxtxbUIgk0dmuMA2Rkg20QE",
                "id": "UgyTDcojDeOvis4AM0B4AaABAg",
                "snippet": {
                    "channelId": "UCuF5t0ziFf7QfoR9_xlti1w",
                    "videoId": "EpyaquDcw1s",
                    "textDisplay": "素敵な動画ありがとうございます☺またこの場で聴きたいです✨✨",
                    "textOriginal": "素敵な動画ありがとうございます☺またこの場で聴きたいです✨✨",
                    "authorDisplayName": "@nao-ln8hx",
                    "authorProfileImageUrl": "https://yt3.ggpht.com/kMvVQQ6NpKz6pctvGPgdoY9ED-ZsAbxHgka2vEeWB1cxXIlx6JhRZTSyJC0uHimYo8rBT5ZQtSs=s48-c-k-c0x00ffffff-no-rj",
                    "authorChannelUrl": "http://www.youtube.com/@nao-ln8hx",
                    "authorChannelId": {
                        "value": "UCaON9s7j0WqrvUNG3mMr9vA"
                    },
                    "canRate": true,
                    "viewerRating": "none",
                    "likeCount": 1,
                    "publishedAt": "2025-11-20T12:03:13Z",
                    "updatedAt": "2025-11-20T12:03:13Z"
                }
            },
            "canReply": true,
            "totalReplyCount": 0,
            "isPublic": true
        }
    }
]