[
    {
        "kind": "youtube#commentThread",
        "etag": "B8kn-kylIUZ0f-qKe3aebRsXCSw",
        "id": "Ugx8boGlW5R20DHdqXd4AaABAg",
        "snippet": {
            "channelId": "UC1K2MgSYvJsGZxwqpEVDThw",
            "videoId": "gg45R3vC7Ls",
            "topLevelComment": {
                "kind": "youtube#comment",
                "etag": "OUGHHjCaNFlsNKqO5mO0cppoOLg",
                "id": "Ugx8boGlW5R20DHdqXd4AaABAg",
                "snippet": {
                    "channelId": "UC1K2MgSYvJsGZxwqpEVDThw",
                    "videoId": "gg45R3vC7Ls",
                    "textDisplay": "It's too song bhaiya ❤❤",
                    "textOriginal": "It's too song bhaiya ❤❤",
                    "authorDisplayName": "@Mayankraj-y3g",
                    "authorProfileImageUrl": "https://yt3.ggpht.com/WuzEzV2CNYV6LfhPK5maHklRpZWwoe6Pb_E-4J9oprRza1oao91mVXx_YSNnUt6nQE28Q6-eVg=s48-c-k-c0x00ffffff-no-rj",
                    "authorChannelUrl": "http://www.youtube.com/@Mayankraj-y3g",
                    "authorChannelId": {
                        "value": "UCN3Jymej6teewD2AMp9H-Sg"
                    },
                    "canRate": true,
                    "viewerRating": "none",
                    "likeCount": 1,
                    "publishedAt": "2025-12-06T09:40:53Z",
                    "updatedAt": "2025-12-06T09:40:53Z"
                }
            },
            "canReply": true,
            "totalReplyCount": 0,
            "isPublic": true
        }
    },
    {
        "kind": "youtube#commentThread",
        "etag": "xbl_TJvR67BFXrGV7Nu0ApEjwG8",
        "id": "UgwdwR1VLjH6djFhhsh4AaABAg",
        "snippet": {
            "channelId": "UC1K2MgSYvJsGZxwqpEVDThw",
            "videoId": "gg45R3vC7Ls",
            "topLevelComment": {
                "kind": "youtube#comment",
                "etag": "kFWCDQUWsfQ_78PA9ujUdgFAah0",
                "id": "UgwdwR1VLjH6djFhhsh4AaABAg",
                "snippet": {
                    "channelId": "UC1K2MgSYvJsGZxwqpEVDThw",
                    "videoId": "gg45R3vC7Ls",
                    "textDisplay": "Nice 🎉🎉❤❤❤",
                    "textOriginal": "Nice 🎉🎉❤❤❤",
                    "authorDisplayName": "@SurendraKumar-p4z8q",
                    "authorProfileImageUrl": "https://yt3.ggpht.com/ytc/AIdro_nuNlfceTDiBSTQUhxQ56YDJFbBu1DjRfTpJMFP6ck9D0x3tsglom8eMUA2blBLpRVU8w=s48-c-k-c0x00ffffff-no-rj",
                    "authorChannelUrl": "http://www.youtube.com/@SurendraKumar-p4z8q",
                    "authorChannelId": {
                        "value": "UCEuqzV1KXFvQkB78yl-My9A"
                    },
                    "canRate": true,
                    "viewerRating": "none",
                    "likeCount": 0,
                    "publishedAt": "2025-11-27T14:40:07Z",
                    "updatedAt": "2025-11-27T14:40:07Z"
                }
            },
            "canReply": true,
            "totalReplyCount": 0,
            "isPublic": true
        }
    },
    {
        "kind": "youtube#commentThread",
        "etag": "lL65aiDDgXCL6ieecq7_PCQAjwU",
        "id": "Ugz5FNQ4tsB5-y4vG_B4AaABAg",
        "snippet": {
            "channelId": "UC1K2MgSYvJsGZxwqpEVDThw",
            "videoId": "gg45R3vC7Ls",
            "topLevelComment": {
                "kind": "youtube#comment",
                "etag": "qY13Z3sdfZTRbGPh2kyC_5C8-Lo",
                "id": "Ugz5FNQ4tsB5-y4vG_B4AaABAg",
                "snippet": {
                    "channelId": "UC1K2MgSYvJsGZxwqpEVDThw",
                    "videoId": "gg45R3vC7Ls",
                    "textDisplay": "Good song 0:19",
                    "textOriginal": "Good song 0:19",
                    "authorDisplayName": "@AjayRao-p3c",
                    "authorProfileImageUrl": "https://yt3.ggpht.com/ytc/AIdro_li0yM6cYLIOWjD11MRFrJBTyO1UpGuxl0HXyI_Shaix_AohWC1X6iVYA2plRVEmtsyaw=s48-c-k-c0x00ffffff-no-rj",
                    "authorChannelUrl": "http://www.youtube.com/@AjayRao-p3c",
                    "authorChannelId": {
                        "value": "UCyZkqFC3qOCuTIc1i7nbleA"
                    },
                    "canRate": true,
                    "viewerRating": "none",
                    "likeCount": 1,
                    "publishedAt": "2025-11-16T11:01:50Z",
                    "updatedAt": "2025-11-16T11:01:50Z"
                }
            },
            "canReply": true,
            "totalReplyCount": 0,
            "isPublic": true
        }
    },
    {
        "kind": "youtube#commentThread",
        "etag": "PEgU4R6oOrsrhj7Q0eCOPec9FwI",
        "id": "UgwMmAwiezIPhkvD47F4AaABAg",
        "snippet": {
            "channelId": "UC1K2MgSYvJsGZxwqpEVDThw",
            "videoId": "gg45R3vC7Ls",
            "topLevelComment": {
                "kind": "youtube#comment",
                "etag": "wgErlycjvXNaLHBy1avcI5aMx9U",
                "id": "UgwMmAwiezIPhkvD47F4AaABAg",
                "snippet": {
                    "channelId": "UC1K2MgSYvJsGZxwqpEVDThw",
                    "videoId": "gg45R3vC7Ls",
                    "textDisplay": "Awesome 😎👍🎉🎉🎉🎉❤❤❤❤",
                    "textOriginal": "Awesome 😎👍🎉🎉🎉🎉❤❤❤❤",
                    "authorDisplayName": "@Music_masti_9",
                    "authorProfileImageUrl": "https://yt3.ggpht.com/ytc/AIdro_lPAu5LcUW1h_9K92DDPIFAt7oKeKn1gaScOAfzdeLy0FyHMrhcwYmEo-u21qNz3kJRkA=s48-c-k-c0x00ffffff-no-rj",
                    "authorChannelUrl": "http://www.youtube.com/@Music_masti_9",
                    "authorChannelId": {
                        "value": "UCkY3JrNntgCn4YRzoEi5U6Q"
                    },
                    "canRate": true,
                    "viewerRating": "none",
                    "likeCount": 1,
                    "publishedAt": "2025-11-16T10:50:17Z",
                    "updatedAt": "2025-11-16T10:50:17Z"
                }
            },
            "canReply": true,
            "totalReplyCount": 1,
            "isPublic": true
        }
    },
    {
        "kind": "youtube#commentThread",
        "etag": "LcFO2tQ0eR_wO95Ewx33wCko62A",
        "id": "UgzNTlldNs6oEN5UT6N4AaABAg",
        "snippet": {
            "channelId": "UC1K2MgSYvJsGZxwqpEVDThw",
            "videoId": "gg45R3vC7Ls",
            "topLevelComment": {
                "kind": "youtube#comment",
                "etag": "3tlGwYcIqmrIv7GDYvRyo5DrZrI",
                "id": "UgzNTlldNs6oEN5UT6N4AaABAg",
                "snippet": {
                    "channelId": "UC1K2MgSYvJsGZxwqpEVDThw",
                    "videoId": "gg45R3vC7Ls",
                    "textDisplay": "Bhai aap khud gaaye ho kya..? Ye search maarne se nhi mil raha h youtube me",
                    "textOriginal": "Bhai aap khud gaaye ho kya..? Ye search maarne se nhi mil raha h youtube me",
                    "authorDisplayName": "@vloggingforfun9745",
                    "authorProfileImageUrl": "https://yt3.ggpht.com/kZQLf78LCWuInjX8bfR3SA3E_EE6U6FPyWJC2Rfgqz4Am8rt5B5r5sK6otcHxd5jz0Ic0ROYUdg=s48-c-k-c0x00ffffff-no-rj",
                    "authorChannelUrl": "http://www.youtube.com/@vloggingforfun9745",
                    "authorChannelId": {
                        "value": "UCPyIKFxTC8Rj-w2Wl8EDo7A"
                    },
                    "canRate": true,
                    "viewerRating": "none",
                    "likeCount": 0,
                    "publishedAt": "2025-11-15T19:02:45Z",
                    "updatedAt": "2025-11-15T19:02:45Z"
                }
            },
            "canReply": true,
            "totalReplyCount": 3,
            "isPublic": true
        }
    },
    {
        "kind": "youtube#commentThread",
        "etag": "kteE5Z89ai_zfGKMWxFdz_1quvQ",
        "id": "Ugy0MoFRn9Ctv-Xd68Z4AaABAg",
        "snippet": {
            "channelId": "UC1K2MgSYvJsGZxwqpEVDThw",
            "videoId": "gg45R3vC7Ls",
            "topLevelComment": {
                "kind": "youtube#comment",
                "etag": "azG_5OLALItGwJOOVdFSSrSYMQY",
                "id": "Ugy0MoFRn9Ctv-Xd68Z4AaABAg",
                "snippet": {
                    "channelId": "UC1K2MgSYvJsGZxwqpEVDThw",
                    "videoId": "gg45R3vC7Ls",
                    "textDisplay": "Nice ❤❤❤❤❤",
                    "textOriginal": "Nice ❤❤❤❤❤",
                    "authorDisplayName": "@WtfMoments-h9t",
                    "authorProfileImageUrl": "https://yt3.ggpht.com/ytc/AIdro_njpOXPzjhVheDIVvxD27i2G0ek5k3HBRYeq_8-E8o0D3WRHKC2n2FCC4BvpgaFl4Vvwg=s48-c-k-c0x00ffffff-no-rj",
                    "authorChannelUrl": "http://www.youtube.com/@WtfMoments-h9t",
                    "authorChannelId": {
                        "value": "UCzVzMINP_RMh9xaBCgYDRNA"
                    },
                    "canRate": true,
                    "viewerRating": "none",
                    "likeCount": 0,
                    "publishedAt": "2025-11-14T13:36:41Z",
                    "updatedAt": "2025-11-14T13:36:41Z"
                }
            },
            "canReply": true,
            "totalReplyCount": 1,
            "isPublic": true
        }
    },
    {
        "kind": "youtube#commentThread",
        "etag": "vtwLrF1dYzoAHSJYS45lOroApCc",
        "id": "Ugwt_dWXUQapNhuqW4Z4AaABAg",
        "snippet": {
            "channelId": "UC1K2MgSYvJsGZxwqpEVDThw",
            "videoId": "gg45R3vC7Ls",
            "topLevelComment": {
                "kind": "youtube#comment",
                "etag": "XonOFXwPtAWeOu-CvKifskBPHYc",
                "id": "Ugwt_dWXUQapNhuqW4Z4AaABAg",
                "snippet": {
                    "channelId": "UC1K2MgSYvJsGZxwqpEVDThw",
                    "videoId": "gg45R3vC7Ls",
                    "textDisplay": "Best hai bhiya 🎉🎉🎉❤❤❤❤ 0:14",
                    "textOriginal": "Best hai bhiya 🎉🎉🎉❤❤❤❤ 0:14",
                    "authorDisplayName": "@MakeMusic-v5q",
                    "authorProfileImageUrl": "https://yt3.ggpht.com/ytc/AIdro_mNkj4pW6jUvChG4gBzsrYlBtzdpsU-SuNMu6MPKVmDoCxY2_D05vAOfPJE2IATJUm0Sw=s48-c-k-c0x00ffffff-no-rj",
                    "authorChannelUrl": "http://www.youtube.com/@MakeMusic-v5q",
                    "authorChannelId": {
                        "value": "UC18mPKNH8qF-_5al12b_fRw"
                    },
                    "canRate": true,
                    "viewerRating": "none",
                    "likeCount": 1,
                    "publishedAt": "2025-11-14T13:35:36Z",
                    "updatedAt": "2025-11-14T13:35:36Z"
                }
            },
            "canReply": true,
            "totalReplyCount": 0,
            "isPublic": true
        }
    },
    {
        "kind": "youtube#commentThread",
        "etag": "CaiW2-MLtIqznmsTpJTckRZfmgM",
        "id": "UgywwkT3ul83jZyPj4N4AaABAg",
        "snippet": {
            "channelId": "UC1K2MgSYvJsGZxwqpEVDThw",
            "videoId": "gg45R3vC7Ls",
            "topLevelComment": {
                "kind": "youtube#comment",
                "etag": "mJmFei5Ig26oEtYESkk1u-0awug",
                "id": "UgywwkT3ul83jZyPj4N4AaABAg",
                "snippet": {
                    "channelId": "UC1K2MgSYvJsGZxwqpEVDThw",
                    "videoId": "gg45R3vC7Ls",
                    "textDisplay": "❤❤❤❤🎉🎉🎉🎉",
                    "textOriginal": "❤❤❤❤🎉🎉🎉🎉",
                    "authorDisplayName": "@UNKNOWN_WRITER_49",
                    "authorProfileImageUrl": "https://yt3.ggpht.com/NIX2FFUeW5GedbeCndxJBWY7ee4y2lKzs0r85hJ-vCWeWwgVYYRKO7fu2PbSOrE08nn76lxQGw=s48-c-k-c0x00ffffff-no-rj",
                    "authorChannelUrl": "http://www.youtube.com/@UNKNOWN_WRITER_49",
                    "authorChannelId": {
                        "value": "UCyZi1c-D0PVk88Bp8ayK7Uw"
                    },
                    "canRate": true,
                    "viewerRating": "none",
                    "likeCount": 0,
                    "publishedAt": "2025-11-14T13:34:11Z",
                    "updatedAt": "2025-11-14T13:34:11Z"
                }
            },
            "canReply": true,
            "totalReplyCount": 0,
            "isPublic": true
        }
    },
    {
        "kind": "youtube#commentThread",
        "etag": "TCfozYgNl7kQwZkpi5tzlVFLZDU",
        "id": "UgzpdMWYsYr3iwrrLgh4AaABAg",
        "snippet": {
            "channelId": "UC1K2MgSYvJsGZxwqpEVDThw",
            "videoId": "gg45R3vC7Ls",
            "topLevelComment": {
                "kind": "youtube#comment",
                "etag": "nPx1SAubaaBpIgzWTJwpO19HzMk",
                "id": "UgzpdMWYsYr3iwrrLgh4AaABAg",
                "snippet": {
                    "channelId": "UC1K2MgSYvJsGZxwqpEVDThw",
                    "videoId": "gg45R3vC7Ls",
                    "textDisplay": "❤❤❤❤🎉🎉🎉🎉🎉 0:20",
                    "textOriginal": "❤❤❤❤🎉🎉🎉🎉🎉 0:20",
                    "authorDisplayName": "@UnpluggedFF",
                    "authorProfileImageUrl": "https://yt3.ggpht.com/X-yfbRPpQuUxiMMdf8ZfQVOXDRrl9ULNj3aDUMbXbfyoREbZzwQi9q_dVzCYZils5TrBbX2Gwg=s48-c-k-c0x00ffffff-no-rj",
                    "authorChannelUrl": "http://www.youtube.com/@UnpluggedFF",
                    "authorChannelId": {
                        "value": "UClpPJu7L-9PnT6qoP-ebo8w"
                    },
                    "canRate": true,
                    "viewerRating": "none",
                    "likeCount": 0,
                    "publishedAt": "2025-11-14T13:33:25Z",
                    "updatedAt": "2025-11-14T13:33:25Z"
                }
            },
            "canReply": true,
            "totalReplyCount": 0,
            "isPublic": true
        }
    },
    {
        "kind": "youtube#commentThread",
        "etag": "a-EgbZUOICNr7i-S2UcELfP2710",
        "id": "UgygBxSAM9SDE3A3XNN4AaABAg",
        "snippet": {
            "channelId": "UC1K2MgSYvJsGZxwqpEVDThw",
            "videoId": "gg45R3vC7Ls",
            "topLevelComment": {
                "kind": "youtube#comment",
                "etag": "ohUmrqvV-Lkd1GSi6ed0_SdMvDw",
                "id": "UgygBxSAM9SDE3A3XNN4AaABAg",
                "snippet": {
                    "channelId": "UC1K2MgSYvJsGZxwqpEVDThw",
                    "videoId": "gg45R3vC7Ls",
                    "textDisplay": "😊😊😊",
                    "textOriginal": "😊😊😊",
                    "authorDisplayName": "@Alicemadam",
                    "authorProfileImageUrl": "https://yt3.ggpht.com/ytc/AIdro_meYAh6NPkc3qZ9RQbztfozX2jknUqc69hcasQTLZa7CCWY6MHmzRI1I6I59gYFhEiQXA=s48-c-k-c0x00ffffff-no-rj",
                    "authorChannelUrl": "http://www.youtube.com/@Alicemadam",
                    "authorChannelId": {
                        "value": "UCLRR5kZ5qhE8zQuDgP9h0hw"
                    },
                    "canRate": true,
                    "viewerRating": "none",
                    "likeCount": 0,
                    "publishedAt": "2025-11-14T13:32:16Z",
                    "updatedAt": "2025-11-14T13:32:16Z"
                }
            },
            "canReply": true,
            "totalReplyCount": 0,
            "isPublic": true
        }
    },
    {
        "kind": "youtube#commentThread",
        "etag": "ed1BcAkIRe0htfgN72me525lFHw",
        "id": "Ugx8fd8BBoCnVnlOZpN4AaABAg",
        "snippet": {
            "channelId": "UC1K2MgSYvJsGZxwqpEVDThw",
            "videoId": "gg45R3vC7Ls",
            "topLevelComment": {
                "kind": "youtube#comment",
                "etag": "ETINkOGCmgLG_WCEz9hXds9V3d8",
                "id": "Ugx8fd8BBoCnVnlOZpN4AaABAg",
                "snippet": {
                    "channelId": "UC1K2MgSYvJsGZxwqpEVDThw",
                    "videoId": "gg45R3vC7Ls",
                    "textDisplay": "❤❤❤",
                    "textOriginal": "❤❤❤",
                    "authorDisplayName": "@HimanshuRao-u1s",
                    "authorProfileImageUrl": "https://yt3.ggpht.com/rnwl4k3KIAiq1vnrGm8paZYqn_hpsATWjZfCOeE5gV7O-idOD_kOvvQ1cXbp8NVYPy-Rm6uH=s48-c-k-c0x00ffffff-no-rj",
                    "authorChannelUrl": "http://www.youtube.com/@HimanshuRao-u1s",
                    "authorChannelId": {
                        "value": "UCsL74KKffPYs15CT0224XBg"
                    },
                    "canRate": true,
                    "viewerRating": "none",
                    "likeCount": 1,
                    "publishedAt": "2025-11-14T12:00:35Z",
                    "updatedAt": "2025-11-14T12:00:35Z"
                }
            },
            "canReply": true,
            "totalReplyCount": 0,
            "isPublic": true
        }
    },
    {
        "kind": "youtube#commentThread",
        "etag": "TAsJyZomUD30q9qNQnFuX5ozcxc",
        "id": "UgwmLxLv03OVpAIUS854AaABAg",
        "snippet": {
            "channelId": "UC1K2MgSYvJsGZxwqpEVDThw",
            "videoId": "gg45R3vC7Ls",
            "topLevelComment": {
                "kind": "youtube#comment",
                "etag": "OJjvbJ2EaVcpQAWEvopk6TJOnHs",
                "id": "UgwmLxLv03OVpAIUS854AaABAg",
                "snippet": {
                    "channelId": "UC1K2MgSYvJsGZxwqpEVDThw",
                    "videoId": "gg45R3vC7Ls",
                    "textDisplay": "Wooww😮😮",
                    "textOriginal": "Wooww😮😮",
                    "authorDisplayName": "@Musiclover77-e6z",
                    "authorProfileImageUrl": "https://yt3.ggpht.com/ytc/AIdro_lPAu5LcUW1h_9K92DDPIFAt7oKeKn1gaScOAfzdeLy0FyHMrhcwYmEo-u21qNz3kJRkA=s48-c-k-c0x00ffffff-no-rj",
                    "authorChannelUrl": "http://www.youtube.com/@Musiclover77-e6z",
                    "authorChannelId": {
                        "value": "UCIquKj1UYWhjfyUGTCbPuEw"
                    },
                    "canRate": true,
                    "viewerRating": "none",
                    "likeCount": 1,
                    "publishedAt": "2025-11-14T11:55:50Z",
                    "updatedAt": "2025-11-14T11:55:50Z"
                }
            },
            "canReply": true,
            "totalReplyCount": 0,
            "isPublic": true
        }
    }
]